geometatool/__init__.py
geometatool/convert.py
geometatool/extract.py
geometatool/formatter.py
geometatool/iso_metadata.py
geometatool/utils.py
geometatool/validate.py
geometatool/geo_profiles/__init__.py
geometatool/geo_profiles/geo_database.py
geometatool/geo_profiles/raster_data.py
geometatool/geo_profiles/vector_data.py
geometatool/iso_standards/19110/19110.zip
geometatool/iso_standards/19110/fcc/1.0/abstract.xsd
geometatool/iso_standards/19110/fcc/1.0/fcc.png
geometatool/iso_standards/19110/fcc/1.0/fcc.xsd
geometatool/iso_standards/19110/fcc/1.0/fcc.zip
geometatool/iso_standards/19110/fcc/1.0/index.html
geometatool/iso_standards/19110/gfc/1.1/exampleInstance.xml
geometatool/iso_standards/19110/gfc/1.1/featureCatalogue.xsd
geometatool/iso_standards/19110/gfc/1.1/gfc.png
geometatool/iso_standards/19110/gfc/1.1/gfc.xsd
geometatool/iso_standards/19110/gfc/1.1/gfc.zip
geometatool/iso_standards/19110/gfc/1.1/index.html
geometatool/iso_standards/19111/19111.zip
geometatool/iso_standards/19111/rbc/1.0/index.html
geometatool/iso_standards/19111/rbc/1.0/rbc.zip
geometatool/iso_standards/19111/rce/1.0/index.html
geometatool/iso_standards/19111/rce/1.0/rce.zip
geometatool/iso_standards/19115/19115.zip
geometatool/iso_standards/19115/19115AllNamespaces.zip
geometatool/iso_standards/19115/-2/gmi/1.0/acquisitionInformation.xsd
geometatool/iso_standards/19115/-2/gmi/1.0/contentInformation.xsd
geometatool/iso_standards/19115/-2/gmi/1.0/dataQualityInformation.xsd
geometatool/iso_standards/19115/-2/gmi/1.0/gmi.xsd
geometatool/iso_standards/19115/-2/gmi/1.0/gmi.zip
geometatool/iso_standards/19115/-2/gmi/1.0/metadataEntitySet.xsd
geometatool/iso_standards/19115/-2/gmi/1.0/spatialRepresentationInformation.xsd
geometatool/iso_standards/19115/-3/cat/1.0/cat.png
geometatool/iso_standards/19115/-3/cat/1.0/cat.xsd
geometatool/iso_standards/19115/-3/cat/1.0/cat.zip
geometatool/iso_standards/19115/-3/cat/1.0/catalogues.xsd
geometatool/iso_standards/19115/-3/cat/1.0/codelistItem.xsd
geometatool-0.1.5.dist-info/METADATA
geometatool-0.1.5.dist-info/WHEEL
geometatool-0.1.5.dist-info/top_level.txt
geometatool-0.1.5.dist-info/RECORD
