Metadata-Version: 2.1
Name: geometatool
Version: 0.1.5
Summary: Geospatial Metadata Toolkit
Home-page: https://github.com/worldbank/geometatool
Author: Kamwoo Lee
Requires-Dist: requests
Requires-Dist: xmltodict
Requires-Dist: pandas
Requires-Dist: geopandas
Requires-Dist: rasterio
Requires-Dist: numpy
Requires-Dist: jsonschema
Requires-Dist: lxml
Requires-Dist: pyproj
